scBC/DWL.py
scBC/__init__.py
scBC/data.py
scBC/model.py
scBC-0.3.2.dist-info/LICENSE
scBC-0.3.2.dist-info/METADATA
scBC-0.3.2.dist-info/WHEEL
scBC-0.3.2.dist-info/top_level.txt
scBC-0.3.2.dist-info/RECORD
