Metadata-Version: 2.1
Name: scBC
Version: 0.3.2
Summary: a single-cell transcriptome Bayesian biClustering framework
Home-page: https://github.com/GYQ-form/scBC
Author: Yuqiao Gong
Author-email: gyq123@sjtu.edu.cn
License: MIT
Keywords: single cell transcriptomics,Biclustering,bioinformatics,variational inference(VI)
Classifier: Programming Language :: Python :: 3
Classifier: License :: OSI Approved :: MIT License
Classifier: Operating System :: OS Independent
License-File: LICENSE
Requires-Dist: scvi-tools (>=0.19.0)
Requires-Dist: biomart
Requires-Dist: requests
Requires-Dist: scipy
